LICENSE
README.md
setup.py
loguru_config/__init__.py
loguru_config/loguru_config.py
loguru_config/parsable_config.py
loguru_config.egg-info/PKG-INFO
loguru_config.egg-info/SOURCES.txt
loguru_config.egg-info/dependency_links.txt
loguru_config.egg-info/requires.txt
loguru_config.egg-info/top_level.txt
loguru_config/utils/__init__.py
loguru_config/utils/loaders.py
loguru_config/utils/parsers.py