Metadata-Version: 2.1
Name: loguru-config
Version: 0.1.0
Summary: Loguru configuration from configuration files.
Home-page: https://github.com/erezinman/loguru-config
Author: Erez Zinman
License: MIT
Download-URL: https://github.com/erezinman/loguru-config/archive/refs/tags/0.1.0.tar.gz
Keywords: loguru,configuration,config,logging,log
Platform: UNKNOWN
Classifier: Development Status :: 3 - Alpha
Classifier: Intended Audience :: Developers
Classifier: License :: OSI Approved :: MIT License
Classifier: Programming Language :: Python :: 3
Classifier: Programming Language :: Python :: 3.7
Classifier: Programming Language :: Python :: 3.8
Classifier: Programming Language :: Python :: 3.9
Classifier: Programming Language :: Python :: 3.10
Classifier: Programming Language :: Python :: 3.11
Classifier: Operating System :: OS Independent
Classifier: Topic :: Software Development :: Libraries :: Python Modules
Classifier: Topic :: System :: Logging
Requires-Python: >=3.7
